Changelog.txt
branching_story.py
create_api_docs.sh
ministory.py
save.py
semantic_stories.py
setup.py
simple_story.py
tutorial.py
tutorial_de.py
TextRPG.egg-info/PKG-INFO
TextRPG.egg-info/SOURCES.txt
TextRPG.egg-info/dependency_links.txt
TextRPG.egg-info/top_level.txt
pyglet/__init__.py
pyglet/clock.py
pyglet/com.py
pyglet/event.py
pyglet/lib.py
pyglet/font/__init__.py
pyglet/font/base.py
pyglet/font/carbon.py
pyglet/font/freetype.py
pyglet/font/freetype_lib.py
pyglet/font/ttf.py
pyglet/font/win32.py
pyglet/gl/__init__.py
pyglet/gl/agl.py
pyglet/gl/gl.py
pyglet/gl/gl_info.py
pyglet/gl/glext_arb.py
pyglet/gl/glext_missing.py
pyglet/gl/glext_nv.py
pyglet/gl/glu.py
pyglet/gl/glu_info.py
pyglet/gl/glx.py
pyglet/gl/glx_info.py
pyglet/gl/glxext_arb.py
pyglet/gl/glxext_mesa.py
pyglet/gl/glxext_nv.py
pyglet/gl/lib.py
pyglet/gl/lib_agl.py
pyglet/gl/lib_glx.py
pyglet/gl/lib_wgl.py
pyglet/gl/wgl.py
pyglet/gl/wgl_info.py
pyglet/gl/wglext_arb.py
pyglet/gl/wglext_nv.py
pyglet/image/__init__.py
pyglet/image/codecs/__init__.py
pyglet/image/codecs/dds.py
pyglet/image/codecs/gdiplus.py
pyglet/image/codecs/gdkpixbuf2.py
pyglet/image/codecs/pil.py
pyglet/image/codecs/png.py
pyglet/image/codecs/pypng.py
pyglet/image/codecs/quicktime.py
pyglet/image/codecs/s3tc.py
pyglet/media/__init__.py
pyglet/media/avbin.py
pyglet/media/procedural.py
pyglet/media/riff.py
pyglet/media/drivers/__init__.py
pyglet/media/drivers/silent.py
pyglet/media/drivers/alsa/__init__.py
pyglet/media/drivers/alsa/asound.py
pyglet/media/drivers/directsound/__init__.py
pyglet/media/drivers/directsound/lib_dsound.py
pyglet/media/drivers/openal/__init__.py
pyglet/media/drivers/openal/lib_alc.py
pyglet/media/drivers/openal/lib_openal.py
pyglet/window/__init__.py
pyglet/window/event.py
pyglet/window/key.py
pyglet/window/mouse.py
pyglet/window/carbon/__init__.py
pyglet/window/carbon/constants.py
pyglet/window/carbon/quartzkey.py
pyglet/window/carbon/types.py
pyglet/window/win32/__init__.py
pyglet/window/win32/constants.py
pyglet/window/win32/types.py
pyglet/window/win32/winkey.py
pyglet/window/xlib/__init__.py
pyglet/window/xlib/cursorfont.py
