Metadata-Version: 1.1
Name: TextRPG
Version: 0.4.8
Summary: ['A simple TextRPG which uses the 1d6 RPG backend module for character management and interaction.  ']
Home-page: http://1w6.org/programme
Author: Arne Babenhauserheide
Author-email: arne_bab@web.de
License: GNU GPL-3 or later
Keywords: ews,rpg,characters,1d6
Platform: any
Classifier: License :: OSI Approved :: GNU General Public License (GPL)
Classifier: Programming Language :: Python
Classifier: Operating System :: OS Independent
Classifier: Topic :: Software Development :: Libraries :: Python Modules
Classifier: Intended Audience :: Developers
Classifier: Intended Audience :: End Users/Desktop
Classifier: Environment :: Console
Classifier: Development Status :: 4 - Beta
Requires: pyglet
Requires: yaml
